<?xml version="1.0" encoding="UTF-8"?>
<vivadoHLSLog:LogRoot xmlns:vivadoHLSLog="www.xilinx.com/vivadoHLSLog">
  <errorLogs>
    <logs>
      <synLog/>
      <simLog/>
      <mgLog/>
      <packageLog/>
      <csimLog/>
    </logs>
  </errorLogs>
  <warningLogs>
    <logs>
      <synLog>
        <logs message="WARNING: [SCHED 204-69] Unable to schedule 'load' operation ('rsbox_load_20', aes.c:388->aes.c:481) on array 'rsbox' due to limited memory ports. Please consider using a memory core with more ports or partitioning the array 'rsbox'." projectName="VLSI_Project" solutionName="solution1" date="2020-05-15T05:06:11.904+0530" type="Warning"/>
        <logs message="WARNING: [SCHED 204-68] The II Violation in module 'InvCipher' (Loop: Loop 1): Unable to enforce a carried dependence constraint (II = 1, distance = 1, offset = 1)&#xA;   between 'load' operation ('rsbox_load_27', aes.c:388->aes.c:481) on array 'rsbox' and 'load' operation ('rsbox_load_29', aes.c:388->aes.c:481) on array 'rsbox'." projectName="VLSI_Project" solutionName="solution1" date="2020-05-15T05:06:11.829+0530" type="Warning"/>
        <logs message="WARNING: [XFORM 203-503] Ignored partial unroll directive for loop 'Loop-3.2' (aes.c:359) because its parent loop or function is pipelined." projectName="VLSI_Project" solutionName="solution1" date="2020-05-15T05:06:09.929+0530" type="Warning"/>
      </synLog>
      <simLog>
        <logs message="WARNING: [XSIM 43-3431] One or more environment variables have been detected which affect the operation of the C compiler. These are typically not set in standard installations and are not tested by Xilinx, however they may be appropriate for your system, so the flow will attempt to continue.  If errors occur, try running xelab with the &quot;-mt off -v 1&quot; switches to see more information from the C compiler. The following environment variables have been detected:&#xA;    LIBRARY_PATH" projectName="VLSI_Project" solutionName="solution1" date="2020-05-15T05:07:30.467+0530" type="Warning"/>
      </simLog>
      <mgLog/>
      <packageLog/>
      <csimLog/>
    </logs>
  </warningLogs>
</vivadoHLSLog:LogRoot>
